fcpw/libslang.so
fcpw/py.cpython-310-x86_64-linux-gnu.so
fcpw/__init__.py
fcpw/libslang-glslang.so
fcpw/libgfx.so
fcpw.libs/libslang-glslang-5945447a.so
fcpw.libs/libslang-c7d58a94.so
fcpw.libs/libgfx-e1cc52e1.so
fcpw-1.2.0.dist-info/WHEEL
fcpw-1.2.0.dist-info/RECORD
fcpw-1.2.0.dist-info/METADATA
fcpw-1.2.0.dist-info/licenses/LICENSE
