Metadata-Version: 2.1
Name: fcpw
Version: 1.2.0
Summary: Python bindings for FCPW
Author: Rohan Sawhney
Classifier: License :: OSI Approved :: MIT License
Project-URL: Homepage, https://github.com/rohan-sawhney/fcpw
Requires-Python: >=3.8
